aiowebuz/__init__.py
aiowebuz/automation.py
aiowebuz/browser.py
aiowebuz/client.py
aiowebuz/downloader.py
aiowebuz/parser.py
aiowebuz/utils.py
aiowebuz-1.0.0.dist-info/LICENSE
aiowebuz-1.0.0.dist-info/METADATA
aiowebuz-1.0.0.dist-info/WHEEL
aiowebuz-1.0.0.dist-info/top_level.txt
aiowebuz-1.0.0.dist-info/RECORD
