Metadata-Version: 2.1
Name: aiowebuz
Version: 1.0.0
Summary: O'zbek tilida mukammal web parsing va avtomatizatsiya kutubxonasi
Home-page: https://github.com/oscoderuz/aiowebuz
Author: oscoder
Author-email: oscoderuz@gmail.com
Project-URL: Bug Reports, https://github.com/oscoderuz/aiowebuz/issues
Project-URL: Source, https://github.com/oscoderuz/aiowebuz
Keywords: web scraping parsing selenium automation uzbek
Classifier: Development Status :: 5 - Production/Stable
Classifier: Intended Audience :: Developers
Classifier: Topic :: Software Development :: Libraries :: Python Modules
Classifier: Topic :: Internet :: WWW/HTTP
Classifier: License :: OSI Approved :: MIT License
Classifier: Programming Language :: Python :: 3
Classifier: Programming Language :: Python :: 3.8
Classifier: Programming Language :: Python :: 3.9
Classifier: Programming Language :: Python :: 3.10
Classifier: Programming Language :: Python :: 3.11
Classifier: Programming Language :: Python :: 3.12
Requires-Python: >=3.8
License-File: LICENSE
Requires-Dist: requests>=2.31.0
Requires-Dist: httpx>=0.25.0
Requires-Dist: beautifulsoup4>=4.12.0
Requires-Dist: lxml>=4.9.0
Requires-Dist: seleniumbase>=4.20.0
Requires-Dist: wget>=3.2
Requires-Dist: pyautogui>=0.9.54
Requires-Dist: pillow>=10.0.0
